{
  "success": true,
  "region_code": "RYZ",
  "region_name": "Рязанская область",
  "base_layer": "RYZ Базовый слой 01.01.2026 07:48:\n\n1) RZ0206 2026-01-01T06:48:55\nPower Нет; Посещение Нет; WO Есть\nВсего активных POWER на сети: 3\n\n10 приоритет:\n- RZ0206; wo Есть;Время 2026-01-01 06:48:12\n\n3 приоритет:\n- RZ0019; wo Нет;Время 2026-01-01 06:51:15\n\n9 приоритет:\n- RZ0120; wo Нет;Время 2026-01-01 06:48:10\n\nОткрытые посещения:\nОткрыто всего посещений: 0\nОткрыто регистраций f gen: 0\n",
  "non_priority": "RYZ Неприоритетные технологии 01.01.2026 07:48:\n\nНедоступно LTE1800:\n1) RZ0206\nНедоступно 3G:\n1) RZ0206\n2) RZ0019\n3) RZ0120\nНедоступно LTE2600:\n1) RZ0120\nНедоступно LTE2300:\n1) RZ0206\n2) RZ0040\n3) RZ0093\n4) RZ0461\n5) RZ0019\n6) RZ0120\n7) RZ0755\n",
  "timestamp": "07:48:03",
  "date": "2026-01-01",
  "full_timestamp": "2026-01-01T07:48:03.784562",
  "stats": {
    "total_bs": 7,
    "base_layer_count": 1,
    "power_problems": 3,
    "non_priority_percentage": 86,
    "base_layer_percentage": 14
  },
  "is_real_data": true,
  "collected_at": "2026-01-01T07:48:03.784562",
  "macroregion": "Центр"
}