{
  "success": true,
  "region_code": "ROS",
  "region_name": "Ростовская область",
  "base_layer": "ROS Базовый слой 30.12.2025 09:33:\n\nВсего активных POWER на сети: 1\n\n10 приоритет:\n- RO0342; wo Нет;Время 2025-12-30 09:01:22\n\nОткрытые посещения:\nОткрыто всего посещений: 0\nОткрыто регистраций f gen: 0\n",
  "non_priority": "ROS Неприоритетные технологии 30.12.2025 09:33:\n\nНедоступно 3G:\n1) RO0342\n2) RO2670\n3) RO0437\nНедоступно LTE800:\n1) RO0342\nНедоступно LTE2600:\n1) RO0342\nНедоступно LTE2100:\n1) RO0342\n2) RO0437\n",
  "timestamp": "09:33:36",
  "date": "2025-12-30",
  "full_timestamp": "2025-12-30T09:33:36.508012",
  "stats": {
    "total_bs": 60,
    "base_layer_count": 0,
    "power_problems": 1,
    "non_priority_percentage": 100,
    "base_layer_percentage": 0
  },
  "is_real_data": true,
  "collected_at": "2025-12-30T09:33:36.508012",
  "macroregion": "ЮГ"
}