{
  "success": true,
  "region_code": "PSK",
  "region_name": "Псковская область",
  "base_layer": "PSK Базовый слой 25.12.2025 19:31:\n\nВсего активных POWER на сети: 1\n\n9 приоритет:\n- PS0115; wo Нет;Время 2025-12-25 19:01:34\n\nОткрытые посещения:\nОткрыто всего посещений: 0\nОткрыто регистраций f gen: 0\n",
  "non_priority": "PSK Неприоритетные технологии 25.12.2025 19:31:\n\nНедоступно 3G:\n1) PS0115\n",
  "timestamp": "19:31:55",
  "date": "2025-12-25",
  "full_timestamp": "2025-12-25T19:31:55.626010",
  "stats": {
    "total_bs": 3,
    "base_layer_count": 0,
    "power_problems": 1,
    "non_priority_percentage": 100,
    "base_layer_percentage": 0
  },
  "is_real_data": true,
  "collected_at": "2025-12-25T19:31:55.626010",
  "macroregion": "Северо-запад"
}