{
  "success": true,
  "region_code": "VLD",
  "region_name": "Владивосток",
  "base_layer": "VLD Базовый слой 26.12.2025 23:30:\n\n1) VV0095 2025-12-26T21:33:04\nPower Да; Посещение Нет; WO Есть\n2) VV0046 2025-12-26T17:22:51\nPower Да; Посещение Нет; WO Нет\n3) VV0862 2025-12-26T14:20:13\nPower Да; Посещение Нет; WO Нет\n4) VV0096 2025-12-26T21:33:04\nPower Да; Посещение Нет; WO Нет\n5) VV0368 2025-12-26T05:10:44\nPower Да; Посещение Нет; WO Есть\n6) VV0456 2025-12-04T16:20:13\nPower Да; Посещение Нет; WO Нет\nВсего активных POWER на сети: 1\n\nОткрытые посещения:\nОткрыто всего посещений: 0\nОткрыто регистраций f gen: 0\n",
  "non_priority": "VLD Неприоритетные технологии 26.12.2025 23:30:\n\nНедоступно LTE1800:\n1) VV0095\n2) VV0046\n3) VV0862\n4) VV0096\n5) VV0456\nНедоступно 3G:\n1) VV0095\n2) VV2108\n3) VV0096\n4) VV0955\n5) VV0456\nНедоступно LTE800:\n1) VV0095\n2) VV0715\n3) VV0096\n4) VV0955\nНедоступно LTE2600:\n1) VV0046\nНедоступно LTE2100:\n1) VV0046\n2) VV2108\n3) VV0096\n4) VV0955\n5) VV0456\nНедоступно LTE2300:\n1) VV0046\n2) VV0416\n3) VV0862\n4) VV0421\n",
  "timestamp": "23:30:10",
  "date": "2025-12-26",
  "full_timestamp": "2025-12-26T23:30:10.966138",
  "stats": {
    "total_bs": 11,
    "base_layer_count": 6,
    "power_problems": 1,
    "non_priority_percentage": 46,
    "base_layer_percentage": 54
  },
  "is_real_data": true,
  "collected_at": "2025-12-26T23:30:10.966138",
  "macroregion": "Байкал и Дальний Восток"
}