{
  "success": true,
  "region_code": "EKT",
  "region_name": "Екатеринбург",
  "base_layer": "EKT Базовый слой 26.12.2025 14:13:\n\n1) EO2141 2025-12-26T13:27:50\nPower Нет; Посещение Нет; WO Есть\n2) EK0553 2025-12-25T22:41:00\nPower Нет; Посещение Да; WO Есть\n3) EK1438 2025-12-26T13:25:30\nPower Да; Посещение Да; WO Есть\n4) EK2436 2025-12-26T12:52:20\nPower Да; Посещение Нет; WO Есть\n5) EK2532 2025-12-26T13:19:22\nPower Да; Посещение Да; WO Есть\n6) EK0124 2025-12-26T13:26:59\nPower Нет; Посещение Нет; WO Есть\n7) EK1242 2025-12-26T10:22:52\nPower Да; Посещение Нет; WO Есть\n8) EK1498 2025-12-26T13:26:59\nPower Да; Посещение Да; WO Есть\n9) EK0694 2025-12-26T11:27:20\nPower Да; Посещение Нет; WO Есть\n10) EK2520 2025-12-26T11:19:23\nPower Да; Посещение Нет; WO Есть\n11) EK1497 2025-12-26T13:26:59\nPower Да; Посещение Нет; WO Нет\n12) EK2269 2025-12-26T13:27:50\nPower Да; Посещение Нет; WO Нет\n13) EK2439 2025-12-26T13:27:50\nPower Да; Посещение Нет; WO Нет\n14) EK1940 2025-12-26T13:27:39\nPower Да; Посещение Нет; WO Нет\n15) EK1045 2025-12-26T13:26:59\nPower Да; Посещение Нет; WO Нет\n16) EK2192 2025-12-26T13:21:50\nPower Нет; Посещение Нет; WO Нет\nВсего активных POWER на сети: 5\n\n10 приоритет:\n- EO2141; wo Есть;Время 2025-12-26 11:26:49\n- EO0084; wo Есть;Время 2025-12-26 11:18:14\n\n3 приоритет:\n- EK0124; wo Есть;Время 2025-12-26 11:27:13\n- EK2192; wo Нет;Время 2025-12-26 11:26:49\n\nОткрытые посещения:\nОткрыто всего посещений: 0\nОткрыто регистраций f gen: 0\n",
  "non_priority": "EKT Неприоритетные технологии 26.12.2025 14:13:\n\nНедоступно LTE1800:\n1) EO2141\n2) EK0553\n3) EK2436\n4) EK2532\n5) EK0124\n6) EK1242\n7) EK0694\n8) EK2520\n9) EK1497\n10) EK2269\n11) EK2439\n12) EK1940\n13) EK2192\nНедоступно 3G:\n1) EK0553\n2) EK2345\n3) EK0124\n4) EK1242\n5) EK1498\n6) EK1497\n7) EK2269\n8) EK2485\n9) EK1045\nНедоступно LTE800:\n1) EO2141\n2) EK2436\n3) EO0084\n4) EK0124\n5) EK1242\n6) EK1498\n7) EK2778\n8) EK1497\n9) EK2269\n10) EK2439\n11) EK1940\n12) EK1045\n13) EK2192\nНедоступно LTE2600:\n1) EK0553\n2) EK1030\n3) EK2436\n4) EK0124\n5) EK0866\n6) EK2520\n7) EK2269\nНедоступно LTE2100:\n1) EK2436\n2) EK2532\n3) EK0124\n4) EK1242\n5) EK1498\n6) EK2520\n7) EK1497\n8) EK2269\n9) EK1940\n10) EK2485\n11) EK1045\nНедоступно LTE2300:\n1) EK2436\n2) EK0294\n3) EK2520\n4) EK2308\n",
  "timestamp": "14:13:15",
  "date": "2025-12-26",
  "full_timestamp": "2025-12-26T14:13:15.816879",
  "stats": {
    "total_bs": 27,
    "base_layer_count": 16,
    "power_problems": 5,
    "non_priority_percentage": 41,
    "base_layer_percentage": 59
  },
  "is_real_data": true,
  "collected_at": "2025-12-26T14:13:15.816879",
  "macroregion": "Урал"
}