{
  "success": true,
  "region_code": "NSK",
  "region_name": "Новосибирская область",
  "base_layer": "NSK Базовый слой 31.12.2025 17:50:\n\n1) NS0050 2025-12-31T13:50:11\nPower Да; Посещение Нет; WO Есть\nВсего активных POWER на сети: 0\n\nОткрытые посещения:\nОткрыто всего посещений: 0\nОткрыто регистраций f gen: 0\n",
  "non_priority": "NSK Неприоритетные технологии 31.12.2025 17:50:\n\nНедоступно LTE1800:\n1) NS0050\nНедоступно 3G:\n1) NS0288\nНедоступно LTE800:\n1) NS0288\nНедоступно LTE2600:\n1) NS0288\nНедоступно LTE2100:\n1) NS0288\n",
  "timestamp": "17:50:24",
  "date": "2025-12-31",
  "full_timestamp": "2025-12-31T17:50:24.800062",
  "stats": {
    "total_bs": 2,
    "base_layer_count": 1,
    "power_problems": 0,
    "non_priority_percentage": 50,
    "base_layer_percentage": 50
  },
  "is_real_data": true,
  "collected_at": "2025-12-31T17:50:24.800062",
  "macroregion": "Сибирь"
}